covid19vaccini/Covid19Vaccini.py
covid19vaccini/__init__.py
covid19vaccini-0.1.1.dist-info/AUTHORS.rst
covid19vaccini-0.1.1.dist-info/LICENSE
covid19vaccini-0.1.1.dist-info/METADATA
covid19vaccini-0.1.1.dist-info/WHEEL
covid19vaccini-0.1.1.dist-info/top_level.txt
covid19vaccini-0.1.1.dist-info/RECORD
