Metadata-Version: 2.1
Name: covid19vaccini
Version: 0.1.1
Summary: A package to handle data related to Covid-19 vaccines in Italy.
Home-page: https://github.com/reale/covid19vaccini
Author: Roberto Reale
Author-email: roberto@reale.me
License: MIT license
Keywords: covid19vaccini
Platform: UNKNOWN
Classifier: Development Status :: 2 - Pre-Alpha
Classifier: Intended Audience :: Developers
Classifier: License :: OSI Approved :: MIT License
Classifier: Natural Language :: English
Classifier: Programming Language :: Python :: 3
Classifier: Programming Language :: Python :: 3.5
Classifier: Programming Language :: Python :: 3.6
Classifier: Programming Language :: Python :: 3.7
Classifier: Programming Language :: Python :: 3.8
Requires-Python: >=3.5
